setup.py
project/__init__.py
projectlib.egg-info/PKG-INFO
projectlib.egg-info/SOURCES.txt
projectlib.egg-info/dependency_links.txt
projectlib.egg-info/top_level.txt