Metadata-Version: 1.0
Name: projectlib
Version: 0.0.1
Summary: zhaowenlei upload projectlib
Home-page: http://liluo.org
Author: liluo
Author-email: zhaowenlei789@sina.com
License: MIT License
Keywords: libproject,project
Platform: any
